prodwatch/__init__.py
prodwatch/logging_config.py
prodwatch/py.typed
prodwatch/exceptions/__init__.py
prodwatch/exceptions/exceptions.py
prodwatch/manager/__init__.py
prodwatch/manager/function_manager.py
prodwatch/manager/manager.py
prodwatch/manager/system_identification.py
prodwatch/manager/types.py
prodwatch/manager/finders/__init__.py
prodwatch/manager/finders/find_class_method.py
prodwatch/manager/finders/find_function.py
prodwatch/manager/finders/find_module_function.py
prodwatch/manager/finders/finder_result.py
prodwatch/manager/wrappers/__init__.py
prodwatch/manager/wrappers/logged_function.py
prodwatch/manager/wrappers/logged_method.py
prodwatch/manager/wrappers/logged_property.py
prodwatch/module_loader/__init__.py
prodwatch/module_loader/loader.py
prodwatch-0.3.0.dist-info/METADATA
prodwatch-0.3.0.dist-info/WHEEL
prodwatch-0.3.0.dist-info/RECORD
