Metadata-Version: 2.4
Name: prodwatch
Version: 0.3.0
Summary: A faster, safer way to log and debug live code.
Project-URL: Homepage, https://getprodwatch.com
Project-URL: Repository, https://github.com/standsleeping/prodwatch.git
Project-URL: Issues, https://github.com/standsleeping/prodwatch/issues
Project-URL: Changelog, https://github.com/standsleeping/prodwatch/blob/main/CHANGELOG.md
Author-email: Ryan Prinz <standsleeping@gmail.com>
Requires-Python: >=3.10
Requires-Dist: requests>=2.32.4
